quaternion/__init__.py
quaternion/core.py
quaternion/functions.py
quaternion/np_functions.py
quaternion/rotate_pdb.py
mindspore_quaternion-0.7.1.dist-info/LICENSE
mindspore_quaternion-0.7.1.dist-info/METADATA
mindspore_quaternion-0.7.1.dist-info/WHEEL
mindspore_quaternion-0.7.1.dist-info/top_level.txt
mindspore_quaternion-0.7.1.dist-info/RECORD
