Metadata-Version: 2.1
Name: mindspore-quaternion
Version: 0.7.1
Summary: Quaternion data structure based on MindSpore Framework
Home-page: https://gitee.com/dechin/mindspore-quaternion
Author: Dechin CHEN
Author-email: dechin.phy@gmail.com
License: MIT Licence
Platform: any
License-File: LICENSE
Requires-Dist: numpy
Requires-Dist: hadder
